{"date": "2023-08-23", "channel_name": "CCTV1", "url": "ctv.112114.xyz", "epg_data": [{"start": "00:27", "desc": "", "end": "00:49", "title": "人口-2023-33"}, {"start": "00:49", "desc": "", "end": "01:17", "title": "今日说法-2023-211"}, {"start": "01:17", "desc": "", "end": "01:46", "title": "人与自然-2023-184"}, {"start": "01:46", "desc": "", "end": "02:16", "title": "晚间新闻"}, {"start": "02:16", "desc": "", "end": "02:28", "title": "美术里的中国-3"}, {"start": "02:28", "desc": "", "end": "02:40", "title": "美术里的中国-4"}, {"start": "02:40", "desc": "", "end": "02:45", "title": "泱泱中华-美丽湿地"}, {"start": "02:45", "desc": "", "end": "02:52", "title": "精彩一刻-2023-1国宝4黄金覆面"}, {"start": "02:52", "desc": "", "end": "04:29", "title": "典籍里的中国（第二季）-9"}, {"start": "04:29", "desc": "", "end": "05:00", "title": "今日说法-2023-211"}, {"start": "05:00", "desc": "", "end": "05:30", "title": "新闻联播"}, {"start": "05:30", "desc": "", "end": "06:00", "title": "人与自然-2023-73"}, {"start": "06:00", "desc": "", "end": "08:36", "title": "朝闻天下"}, {"start": "08:36", "desc": "", "end": "09:26", "title": "生活早参考-特别节目（生活圈）2023-167"}, {"start": "09:26", "desc": "", "end": "10:15", "title": "平凡之路第22集"}, {"start": "10:15", "desc": "", "end": "11:03", "title": "平凡之路第23集"}, {"start": "11:03", "desc": "", "end": "11:51", "title": "平凡之路第24集"}, {"start": "11:51", "desc": "", "end": "11:55", "title": "2023秘境之眼-213"}, {"start": "11:55", "desc": "", "end": "12:00", "title": "寻古中国-33宣传片-1"}, {"start": "12:00", "desc": "", "end": "12:35", "title": "新闻30分"}, {"start": "12:35", "desc": "", "end": "13:10", "title": "今日说法-2023-212"}, {"start": "13:10", "desc": "", "end": "13:57", "title": "我们的日子第10集"}, {"start": "13:57", "desc": "", "end": "14:47", "title": "我们的日子第11集"}, {"start": "14:47", "desc": "", "end": "15:34", "title": "我们的日子第12集"}, {"start": "15:34", "desc": "", "end": "16:22", "title": "我们的日子第13集"}, {"start": "16:22", "desc": "", "end": "17:12", "title": "我们的日子第14集"}, {"start": "17:12", "desc": "", "end": "17:31", "title": "第一动画乐园-2023-435"}, {"start": "17:31", "desc": "", "end": "17:57", "title": "第一动画乐园-2023-436"}, {"start": "17:57", "desc": "", "end": "18:00", "title": "第一动画乐园-2022-720"}, {"start": "18:00", "desc": "", "end": "18:02", "title": "2023秘境之眼-213"}, {"start": "18:02", "desc": "", "end": "19:00", "title": "故事中国2023-238 大运河之歌6"}, {"start": "19:00", "desc": "", "end": "19:39", "title": "新闻联播"}, {"start": "19:39", "desc": "", "end": "20:01", "title": "焦点访谈"}, {"start": "20:01", "desc": "", "end": "20:06", "title": "前情提要- 《冰雪尖刀连》第18集"}, {"start": "20:06", "desc": "", "end": "20:57", "title": "冰雪尖刀连18/24"}, {"start": "20:57", "desc": "", "end": "21:01", "title": "前情提要- 《冰雪尖刀连》第19集"}, {"start": "21:01", "desc": "", "end": "22:00", "title": "冰雪尖刀连19/24"}, {"start": "22:00", "desc": "", "end": "22:34", "title": "晚间新闻"}, {"start": "22:34", "desc": "", "end": "23:30", "title": "故事中国2023-241 野性四季：珍稀野生动物在中国3"}, {"start": "23:30", "desc": "", "end": "23:59", "title": "古韵新声-精编10"}]}
